bitcoin_usb/__init__.py
bitcoin_usb/address_types.py
bitcoin_usb/device.py
bitcoin_usb/device_scripts/trezor_firmware.py
bitcoin_usb/dialogs.py
bitcoin_usb/hwi_quick.py
bitcoin_usb/i18n.py
bitcoin_usb/icons/loader-icon.svg
bitcoin_usb/install_udev.sh
bitcoin_usb/psbt_tools.py
bitcoin_usb/seed_tools.py
bitcoin_usb/software_signer.py
bitcoin_usb/spinning_button.py
bitcoin_usb/tool_gui.py
bitcoin_usb/udevwrapper.py
bitcoin_usb/usb_gui.py
bitcoin_usb/util.py
bitcoin_usb-0.7.8.dist-info/LICENSE
bitcoin_usb-0.7.8.dist-info/METADATA
bitcoin_usb-0.7.8.dist-info/WHEEL
bitcoin_usb-0.7.8.dist-info/RECORD
