Metadata-Version: 2.1
Name: bitcoin-usb
Version: 0.7.8
Summary: Wrapper around hwi, such that one can sign bdk PSBTs directly
Home-page: https://github.com/andreasgriffin/bitcoin-usb
License: GPL-3.0
Author: andreasgriffin
Author-email: andreasgriffin@proton.me
Requires-Python: >=3.8.1,<3.13
Classifier: License :: OSI Approved :: GNU General Public License v3 (GPLv3)
Classifier: Programming Language :: Python :: 3
Classifier: Programming Language :: Python :: 3.9
Classifier: Programming Language :: Python :: 3.10
Classifier: Programming Language :: Python :: 3.11
Classifier: Programming Language :: Python :: 3.12
Requires-Dist: bdkpython (>=0.32.0,<0.33.0)
Requires-Dist: hwi (>=3.0.0,<4.0.0)
Requires-Dist: mnemonic (>=0.21,<0.22)
Requires-Dist: pyqt6 (>=6.6.1,<7.0.0)
Requires-Dist: python-bitcointx (==1.1.4)
Requires-Dist: requests (>=2.32.3,<3.0.0)
Requires-Dist: trezor (>=0.13.9,<0.14.0)
